{
    "$schema": "https://schema.management.azure.com/schemas/2015-01-01/deploymentParameters.json#",
    "contentVersion": "1.0.0.0",
    "parameters": {
        "fw-internal-ip": {
            "value": "172.25.1.36"
        },
        "RT-rda-name":{
            "value": "eoe-prod-sub-rda"
        },
        "RT-rdh-name":{
          "value": "eoe-prod-sub-rdh"
        },
        "RT-data-name":{
          "value": "eoe-prod-sub-data"
        },
        "RT-app-name":{
          "value": "eoe-prod-sub-app"
        },
        "RT-core-name":{
          "value": "eoe-prod-sub-core"
        },
        "RT-web-name":{
          "value": "eoe-prod-sub-web"
        },
        "RT-test-name":{
          "value": "eoe-prod-sub-test"
        },
        "RT-mgmt-name":{
          "value": "eoe-prod-sub-mgmt"
        },
        "vNetPrefix": {
            "value": "172.25.0.0/16"
        }
    }
}